sqs_launcher/__init__.py
sqs_listener/__init__.py
sqs_listener/daemon.py
pySqsListener-0.9.0.dist-info/LICENSE
pySqsListener-0.9.0.dist-info/METADATA
pySqsListener-0.9.0.dist-info/WHEEL
pySqsListener-0.9.0.dist-info/top_level.txt
pySqsListener-0.9.0.dist-info/RECORD
