Metadata-Version: 2.1
Name: pySqsListener
Version: 0.9.0
Summary: A simple Python SQS utility package
Home-page: https://github.com/jegesh/python-sqs-listener
Author: Yaakov Gesher
Author-email: yaakov@gesher.net
License: Apache Software License
Keywords: aws sqs listener and message launcher
Platform: UNKNOWN
Classifier: Development Status :: 4 - Beta
Classifier: Intended Audience :: Developers
Classifier: Topic :: Software Development :: Libraries
Classifier: License :: OSI Approved :: Apache Software License
Classifier: Programming Language :: Python :: 2.7
Classifier: Programming Language :: Python :: 3.6
Requires-Dist: boto3
